pdfino/__init__.py
pdfino/cli.py
pdfino/discover.py
pdfino/pandoc.py
pdfino/render.py
pdfino_cli-0.1.0.dist-info/METADATA
pdfino_cli-0.1.0.dist-info/WHEEL
pdfino_cli-0.1.0.dist-info/entry_points.txt
pdfino_cli-0.1.0.dist-info/licenses/LICENSE
pdfino_cli-0.1.0.dist-info/RECORD
