Metadata-Version: 2.4
Name: pdfino-cli
Version: 0.1.0
Summary: Convert .ino/.py files in the current directory into PDFs via Markdown + Pandoc.
Author: GG
License: MIT
License-File: LICENSE
Keywords: arduino,listing,markdown,pandoc,pdf
Classifier: Environment :: Console
Classifier: License :: OSI Approved :: MIT License
Classifier: Programming Language :: Python :: 3
Classifier: Topic :: Text Processing
Requires-Python: >=3.10
